odia/__init__.py
odia/functions.py
odia/greet.py
odia-0.0.7.dist-info/LICENSE
odia-0.0.7.dist-info/METADATA
odia-0.0.7.dist-info/WHEEL
odia-0.0.7.dist-info/top_level.txt
odia-0.0.7.dist-info/RECORD
