Metadata-Version: 2.1
Name: odia
Version: 0.0.7
Summary: Odia language
Home-page: https://github.com/biranchi2018/odia
Author: Biranchi Narayan Nayak
Author-email: biranchi125@gmail.com
License: UNKNOWN
Platform: UNKNOWN
Classifier: Programming Language :: Python :: 3
Classifier: License :: OSI Approved :: MIT License
Classifier: Operating System :: OS Independent
Requires-Python: >=3.6
